my_test_poetry/README.md
my_test_poetry/test.py
my_test_poetry-0.1.0.dist-info/WHEEL
my_test_poetry-0.1.0.dist-info/METADATA
my_test_poetry-0.1.0.dist-info/RECORD
